bhut/__init__.py
bhut/api.py
bhut/backends/__init__.py
bhut/backends/base.py
bhut/backends/dask_.py
bhut/backends/numpy_.py
bhut/space/__init__.py
bhut/space/bbox.py
bhut/traverse/__init__.py
bhut/traverse/bh.py
bhut/traverse/kernels.py
bhut/tree/__init__.py
bhut/tree/build.py
bhut/tree/node.py
bhut/tree/refit.py
bhut/utils/__init__.py
bhut/utils/morton.py
bhut-0.1.3.dist-info/METADATA
bhut-0.1.3.dist-info/WHEEL
bhut-0.1.3.dist-info/top_level.txt
bhut-0.1.3.dist-info/RECORD
