Metadata-Version: 2.4
Name: bhut
Version: 0.1.3
Summary: Barnes-Hut N-body accelerator that is array-agnostic (NumPy/Dask)
Author: Matthias Baer
License: MIT
Project-URL: Homepage, https://github.com/bhut-dev/bhut
Project-URL: Repository, https://github.com/bhut-dev/bhut
Classifier: Development Status :: 3 - Alpha
Classifier: Intended Audience :: Science/Research
Classifier: License :: OSI Approved :: MIT License
Classifier: Programming Language :: Python :: 3
Classifier: Programming Language :: Python :: 3.10
Classifier: Programming Language :: Python :: 3.11
Classifier: Programming Language :: Python :: 3.12
Classifier: Topic :: Scientific/Engineering :: Physics
Requires-Python: >=3.10
Requires-Dist: numpy>=1.23
Requires-Dist: dask[array]>=2024.1.0
Provides-Extra: accel
Requires-Dist: numba>=0.59; extra == "accel"
Provides-Extra: dev
Requires-Dist: pytest; extra == "dev"
Requires-Dist: hypothesis; extra == "dev"
Requires-Dist: pytest-cov; extra == "dev"
Requires-Dist: ruff; extra == "dev"
Requires-Dist: mypy; extra == "dev"
